Metadata-Version: 2.1
Name: redis-events
Version: 0.0.2
Summary: Event based distributed computing using Redis and asyncio
Home-page: https://github.com/3jackdaws/redis-events
Author: Ian Murphy
Author-email: 3jackdaws@gmail.com
License: MIT
Platform: UNKNOWN
Classifier: Programming Language :: Python :: 3
Classifier: License :: OSI Approved :: MIT License
Classifier: Operating System :: OS Independent
